syncseed/__init__.py
syncseed/seed_exchange.py
syncseed/syncseed.py
syncseed-1.1.0.dist-info/LICENSE.md
syncseed-1.1.0.dist-info/METADATA
syncseed-1.1.0.dist-info/WHEEL
syncseed-1.1.0.dist-info/top_level.txt
syncseed-1.1.0.dist-info/RECORD
