Metadata-Version: 2.1
Name: syncseed
Version: 1.1.0
Summary: A synchronized seed-based authentication system
Home-page: https://github.com/lycanthropy3301/syncseed
Author: Kavin
Author-email: kavin.muthuselvan@gmail.com
Project-URL: Bug Tracker, https://github.com/lycanthropy3301/syncseed/issues
Classifier: Programming Language :: Python :: 3
Classifier: License :: OSI Approved :: MIT License
Classifier: Operating System :: OS Independent
Requires-Python: >=3.6
License-File: LICENSE.md
Requires-Dist: randomgen
Requires-Dist: numpy
